Metadata-Version: 2.1
Name: dzmymodule
Version: 1.4
Summary: da
Author: NeLAR
Author-email: kastamata91@gmail.com
Classifier: Programming Language :: Python :: 3
Classifier: License :: OSI Approved :: MIT License
Classifier: Operating System :: OS Independent
Requires-Python: >=3.6
